Source/BZ.py
Source/__init__.py
Source/bands.py
Source/main-Zachary’s MacBook Pro.py
Source/main.py
castep2fs-1.0.4.dist-info/METADATA
castep2fs-1.0.4.dist-info/PKG-INFO-Zachary’s MacBook Pro
castep2fs-1.0.4.dist-info/SOURCES-Zachary’s MacBook Pro.txt
castep2fs-1.0.4.dist-info/WHEEL
castep2fs-1.0.4.dist-info/entry_points.txt
castep2fs-1.0.4.dist-info/requires-Zachary’s MacBook Pro.txt
castep2fs-1.0.4.dist-info/top_level.txt
castep2fs-1.0.4.dist-info/RECORD
